LICENSE.txt
MANIFEST.in
README.rst
requirements.txt
setup.py
babylon/__init__.py
babylon/templatetags/__init__.py
babylon/templatetags/babylon_cache.py
django_babylon.egg-info/PKG-INFO
django_babylon.egg-info/SOURCES.txt
django_babylon.egg-info/dependency_links.txt
django_babylon.egg-info/requires.txt
django_babylon.egg-info/top_level.txt