Metadata-Version: 1.0
Name: django-babylon
Version: 0.0.3
Summary: Django infinite caching for mandems.
Home-page: https://github.com/radiosilence/django-babylon
Author: James Cleveland
Author-email: jamescleveland@gmail.com
License: LICENSE.txt
Platform: UNKNOWN
